data/ip_library/mem_sram_sp/rtl/sram_sp.v
// Synchronous single-port SRAM — 1 read/write port, registered output.
module sram_sp #(parameter DW = 8, parameter AW = 8) (
    input              clk,
    input              we,                 // write enable
    input  [AW-1:0]    addr,
    input  [DW-1:0]    din,
    output reg [DW-1:0] dout
);
    reg [DW-1:0] mem [0:(1<<AW)-1];
    always @(posedge clk) begin
        if (we) mem[addr] <= din;          // write
        dout <= mem[addr];                 // synchronous read
    end
endmodule

data/ip_library/mem_sram_sp/tb/sram_sp_tb.v
`timescale 1ns/1ps
module sram_sp_tb;
    localparam DW=8, AW=4;
    reg clk=0, we=0; reg [AW-1:0] addr=0; reg [DW-1:0] din=0; wire [DW-1:0] dout;
    integer i, errors=0;
    sram_sp #(.DW(DW), .AW(AW)) dut(.clk(clk), .we(we), .addr(addr), .din(din), .dout(dout));
    always #5 clk=~clk;
    initial begin
        $dumpfile("design.vcd"); $dumpvars(0, sram_sp_tb);
        for (i=0;i<16;i=i+1) begin @(negedge clk); we=1; addr=i; din=i*3+1; end
        @(negedge clk); we=0;
        for (i=0;i<16;i=i+1) begin
            @(negedge clk); addr=i; @(posedge clk); #1;
            if (dout !== (i*3+1)) begin errors=errors+1; $display("MISMATCH addr %0d: got %0d exp %0d", i, dout, i*3+1); end
        end
        if (errors==0) $display("PASS: single-port SRAM ok"); else $display("FAIL: %0d errors", errors);
        $finish;
    end
endmodule

data/ip_library/mem_sram_sp/tb/design.vcd
$date
	Mon Jun 22 16:45:02 2026
$end
$version
	Icarus Verilog
$end
$timescale
	1ps
$end
$scope module sram_sp_tb $end
$var wire 8 ! dout [7:0] $end
$var reg 4 " addr [3:0] $end
$var reg 1 # clk $end
$var reg 8 $ din [7:0] $end
$var reg 1 % we $end
$var integer 32 & errors [31:0] $end
$var integer 32 ' i [31:0] $end
$scope module dut $end
$var wire 4 ( addr [3:0] $end
$var wire 1 # clk $end
$var wire 8 ) din [7:0] $end
$var wire 1 % we $end
$var reg 8 * dout [7:0] $end
$upscope $end
$upscope $end
$enddefinitions $end
#0
$dumpvars
bx *
b0 )
b0 (
b0 '
b0 &
0%
b0 $
0#
b0 "
bx !
$end
#5000
1#
#10000
b1 '
b1 $
b1 )
1%
0#
#15000
1#
#20000
b10 '
b100 $
b100 )
b1 "
b1 (
0#
#25000
1#
#30000
b11 '
b111 $
b111 )
b10 "
b10 (
0#
#35000
1#
#40000
b100 '
b1010 $
b1010 )
b11 "
b11 (
0#
#45000
1#
#50000
b101 '
b1101 $
b1101 )
b100 "
b100 (
0#
#55000
1#
#60000
b110 '
b10000 $
b10000 )
b101 "
b101 (
0#
#65000
1#
#70000
b111 '
b10011 $
b10011 )
b110 "
b110 (
0#
#75000
1#
#80000
b1000 '
b10110 $
b10110 )
b111 "
b111 (
0#
#85000
1#
#90000
b1001 '
b11001 $
b11001 )
b1000 "
b1000 (
0#
#95000
1#
#100000
b1010 '
b11100 $
b11100 )
b1001 "
b1001 (
0#
#105000
1#
#110000
b1011 '
b11111 $
b11111 )
b1010 "
b1010 (
0#
#115000
1#
#120000
b1100 '
b100010 $
b100010 )
b1011 "
b1011 (
0#
#125000
1#
#130000
b1101 '
b100101 $
b100101 )
b1100 "
b1100 (
0#
#135000
1#
#140000
b1110 '
b101000 $
b101000 )
b1101 "
b1101 (
0#
#145000
1#
#150000
b1111 '
b101011 $
b101011 )
b1110 "
b1110 (
0#
#155000
1#
#160000
b10000 '
b101110 $
b101110 )
b1111 "
b1111 (
0#
#165000
1#
#170000
b0 '
0%
0#
#175000
b101110 !
b101110 *
1#
#180000
b0 "
b0 (
0#
#185000
b1 !
b1 *
1#
#186000
b1 '
#190000
b1 "
b1 (
0#
#195000
b100 !
b100 *
1#
#196000
b10 '
#200000
b10 "
b10 (
0#
#205000
b111 !
b111 *
1#
#206000
b11 '
#210000
b11 "
b11 (
0#
#215000
b1010 !
b1010 *
1#
#216000
b100 '
#220000
b100 "
b100 (
0#
#225000
b1101 !
b1101 *
1#
#226000
b101 '
#230000
b101 "
b101 (
0#
#235000
b10000 !
b10000 *
1#
#236000
b110 '
#240000
b110 "
b110 (
0#
#245000
b10011 !
b10011 *
1#
#246000
b111 '
#250000
b111 "
b111 (
0#
#255000
b10110 !
b10110 *
1#
#256000
b1000 '
#260000
b1000 "
b1000 (
0#
#265000
b11001 !
b11001 *
1#
#266000
b1001 '
#270000
b1001 "
b1001 (
0#
#275000
b11100 !
b11100 *
1#
#276000
b1010 '
#280000
b1010 "
b1010 (
0#
#285000
b11111 !
b11111 *
1#
#286000
b1011 '
#290000
b1011 "
b1011 (
0#
#295000
b100010 !
b100010 *
1#
#296000
b1100 '
#300000
b1100 "
b1100 (
0#
#305000
b100101 !
b100101 *
1#
#306000
b1101 '
#310000
b1101 "
b1101 (
0#
#315000
b101000 !
b101000 *
1#
#316000
b1110 '
#320000
b1110 "
b1110 (
0#
#325000
b101011 !
b101011 *
1#
#326000
b1111 '
#330000
b1111 "
b1111 (
0#
#335000
b101110 !
b101110 *
1#
#336000
b10000 '
