data/ip_library/mem_regfile/rtl/regfile.v
// 2-read, 1-write register file with combinational read (x0 not special).
module regfile #(parameter DW = 32, parameter AW = 5) (
    input              clk,
    input              we,
    input  [AW-1:0]    waddr, input [DW-1:0] wdata,
    input  [AW-1:0]    raddr1, output [DW-1:0] rdata1,
    input  [AW-1:0]    raddr2, output [DW-1:0] rdata2
);
    reg [DW-1:0] regs [0:(1<<AW)-1];
    integer i; initial for (i=0;i<(1<<AW);i=i+1) regs[i]=0;
    always @(posedge clk) if (we) regs[waddr] <= wdata;
    assign rdata1 = regs[raddr1];
    assign rdata2 = regs[raddr2];
endmodule

data/ip_library/mem_regfile/tb/regfile_tb.v
`timescale 1ns/1ps
module regfile_tb;
    reg clk=0, we=0; reg [4:0] wa=0,ra1=0,ra2=0; reg [31:0] wd=0; wire [31:0] rd1,rd2;
    integer i, errors=0;
    regfile dut(.clk(clk),.we(we),.waddr(wa),.wdata(wd),.raddr1(ra1),.rdata1(rd1),.raddr2(ra2),.rdata2(rd2));
    always #5 clk=~clk;
    initial begin
        $dumpfile("design.vcd"); $dumpvars(0, regfile_tb);
        for (i=1;i<8;i=i+1) begin @(negedge clk); we=1; wa=i; wd=i*32'h1111; end
        @(negedge clk); we=0;
        for (i=1;i<8;i=i+1) begin #1; ra1=i; #1;
            if (rd1 !== i*32'h1111) begin errors=errors+1; $display("MISMATCH r%0d", i); end end
        if (errors==0) $display("PASS: register file ok"); else $display("FAIL: %0d", errors);
        $finish;
    end
endmodule

data/ip_library/mem_regfile/tb/design.vcd
$date
	Mon Jun 22 16:02:54 2026
$end
$version
	Icarus Verilog
$end
$timescale
	1ps
$end
$scope module regfile_tb $end
$var wire 32 ! rd2 [31:0] $end
$var wire 32 " rd1 [31:0] $end
$var reg 1 # clk $end
$var reg 5 $ ra1 [4:0] $end
$var reg 5 % ra2 [4:0] $end
$var reg 5 & wa [4:0] $end
$var reg 32 ' wd [31:0] $end
$var reg 1 ( we $end
$var integer 32 ) errors [31:0] $end
$var integer 32 * i [31:0] $end
$scope module dut $end
$var wire 1 # clk $end
$var wire 5 + raddr1 [4:0] $end
$var wire 5 , raddr2 [4:0] $end
$var wire 32 - rdata1 [31:0] $end
$var wire 32 . rdata2 [31:0] $end
$var wire 5 / waddr [4:0] $end
$var wire 32 0 wdata [31:0] $end
$var wire 1 ( we $end
$var integer 32 1 i [31:0] $end
$upscope $end
$upscope $end
$enddefinitions $end
#0
$dumpvars
b100000 1
b0 0
b0 /
b0 .
b0 -
b0 ,
b0 +
b1 *
b0 )
0(
b0 '
b0 &
b0 %
b0 $
0#
b0 "
b0 !
$end
#5000
1#
#10000
b10 *
b1000100010001 '
b1000100010001 0
b1 &
b1 /
1(
0#
#15000
1#
#20000
b11 *
b10001000100010 '
b10001000100010 0
b10 &
b10 /
0#
#25000
1#
#30000
b100 *
b11001100110011 '
b11001100110011 0
b11 &
b11 /
0#
#35000
1#
#40000
b101 *
b100010001000100 '
b100010001000100 0
b100 &
b100 /
0#
#45000
1#
#50000
b110 *
b101010101010101 '
b101010101010101 0
b101 &
b101 /
0#
#55000
1#
#60000
b111 *
b110011001100110 '
b110011001100110 0
b110 &
b110 /
0#
#65000
1#
#70000
b1000 *
b111011101110111 '
b111011101110111 0
b111 &
b111 /
0#
#75000
1#
#80000
b1 *
0(
0#
#81000
b1000100010001 "
b1000100010001 -
b1 $
b1 +
#82000
b10 *
#83000
b10001000100010 "
b10001000100010 -
b10 $
b10 +
#84000
b11 *
#85000
b11001100110011 "
b11001100110011 -
b11 $
b11 +
1#
#86000
b100 *
#87000
b100010001000100 "
b100010001000100 -
b100 $
b100 +
#88000
b101 *
#89000
b101010101010101 "
b101010101010101 -
b101 $
b101 +
#90000
b110 *
0#
#91000
b110011001100110 "
b110011001100110 -
b110 $
b110 +
#92000
b111 *
#93000
b111011101110111 "
b111011101110111 -
b111 $
b111 +
#94000
b1000 *
