data/ip_library/mem_rom_sync/rtl/rom_sync.v
// Synchronous ROM — registered output, content baked into the logic.
module rom_sync #(parameter DW = 8, parameter AW = 4) (
    input              clk,
    input  [AW-1:0]    addr,
    output reg [DW-1:0] dout
);
    always @(posedge clk) begin
        case (addr)
            4'd0: dout <= 8'h0A; 4'd1: dout <= 8'h1B; 4'd2: dout <= 8'h2C; 4'd3: dout <= 8'h3D;
            4'd4: dout <= 8'h4E; 4'd5: dout <= 8'h5F; 4'd6: dout <= 8'h60; 4'd7: dout <= 8'h71;
            default: dout <= 8'hFF;
        endcase
    end
endmodule

data/ip_library/mem_rom_sync/tb/rom_sync_tb.v
`timescale 1ns/1ps
module rom_sync_tb;
    reg clk=0; reg [3:0] addr=0; wire [7:0] dout; integer errors=0;
    reg [7:0] exp [0:7];
    rom_sync dut(.clk(clk), .addr(addr), .dout(dout));
    always #5 clk=~clk;
    initial begin
        $dumpfile("design.vcd"); $dumpvars(0, rom_sync_tb);
        exp[0]=8'h0A; exp[1]=8'h1B; exp[2]=8'h2C; exp[3]=8'h3D;
        exp[4]=8'h4E; exp[5]=8'h5F; exp[6]=8'h60; exp[7]=8'h71;
        begin : chk integer i;
            for (i=0;i<8;i=i+1) begin @(negedge clk); addr=i; @(posedge clk); #1;
                if (dout !== exp[i]) begin errors=errors+1; $display("MISMATCH %0d", i); end end
        end
        if (errors==0) $display("PASS: ROM ok"); else $display("FAIL: %0d", errors);
        $finish;
    end
endmodule

data/ip_library/mem_rom_sync/tb/design.vcd
$date
	Mon Jun 22 16:02:54 2026
$end
$version
	Icarus Verilog
$end
$timescale
	1ps
$end
$scope module rom_sync_tb $end
$var wire 8 ! dout [7:0] $end
$var reg 4 " addr [3:0] $end
$var reg 1 # clk $end
$var integer 32 $ errors [31:0] $end
$scope module dut $end
$var wire 4 % addr [3:0] $end
$var wire 1 # clk $end
$var reg 8 & dout [7:0] $end
$upscope $end
$scope begin chk $end
$var integer 32 ' i [31:0] $end
$upscope $end
$upscope $end
$enddefinitions $end
#0
$dumpvars
b0 '
bx &
b0 %
b0 $
0#
b0 "
bx !
$end
#5000
b1010 !
b1010 &
1#
#10000
0#
#15000
1#
#16000
b1 '
#20000
b1 "
b1 %
0#
#25000
b11011 !
b11011 &
1#
#26000
b10 '
#30000
b10 "
b10 %
0#
#35000
b101100 !
b101100 &
1#
#36000
b11 '
#40000
b11 "
b11 %
0#
#45000
b111101 !
b111101 &
1#
#46000
b100 '
#50000
b100 "
b100 %
0#
#55000
b1001110 !
b1001110 &
1#
#56000
b101 '
#60000
b101 "
b101 %
0#
#65000
b1011111 !
b1011111 &
1#
#66000
b110 '
#70000
b110 "
b110 %
0#
#75000
b1100000 !
b1100000 &
1#
#76000
b111 '
#80000
b111 "
b111 %
0#
#85000
b1110001 !
b1110001 &
1#
#86000
b1000 '
