data/ip_library/mem_sram_be/rtl/sram_be.v
// Single-port SRAM with per-byte write strobes (NB bytes wide).
module sram_be #(parameter NB = 4, parameter AW = 8) (
    input                clk,
    input  [NB-1:0]      be,               // one strobe per byte lane
    input  [AW-1:0]      addr,
    input  [NB*8-1:0]    din,
    output reg [NB*8-1:0] dout
);
    reg [NB*8-1:0] mem [0:(1<<AW)-1];
    integer i;
    always @(posedge clk) begin
        for (i=0;i<NB;i=i+1) if (be[i]) mem[addr][i*8 +: 8] <= din[i*8 +: 8];
        dout <= mem[addr];
    end
endmodule

data/ip_library/mem_sram_be/tb/sram_be_tb.v
`timescale 1ns/1ps
module sram_be_tb;
    localparam NB=4, AW=4;
    reg clk=0; reg [NB-1:0] be=0; reg [AW-1:0] addr=0; reg [NB*8-1:0] din=0; wire [NB*8-1:0] dout;
    integer errors=0;
    sram_be #(.NB(NB),.AW(AW)) dut(.clk(clk),.be(be),.addr(addr),.din(din),.dout(dout));
    always #5 clk=~clk;
    initial begin
        $dumpfile("design.vcd"); $dumpvars(0, sram_be_tb);
        @(negedge clk); be=4'b1111; addr=2; din=32'hDEADBEEF;     // full write
        @(negedge clk); be=4'b0010; addr=2; din=32'h0000FF00;     // write byte 1 only
        @(negedge clk); be=0; addr=2; @(posedge clk); #1;
        if (dout !== 32'hDEADFFEF) begin errors=1; $display("MISMATCH got %h", dout); end
        if (errors==0) $display("PASS: byte-enable SRAM ok"); else $display("FAIL");
        $finish;
    end
endmodule

data/ip_library/mem_sram_be/tb/design.vcd
$date
	Mon Jun 22 16:02:54 2026
$end
$version
	Icarus Verilog
$end
$timescale
	1ps
$end
$scope module sram_be_tb $end
$var wire 32 ! dout [31:0] $end
$var reg 4 " addr [3:0] $end
$var reg 4 # be [3:0] $end
$var reg 1 $ clk $end
$var reg 32 % din [31:0] $end
$var integer 32 & errors [31:0] $end
$scope module dut $end
$var wire 4 ' addr [3:0] $end
$var wire 4 ( be [3:0] $end
$var wire 1 $ clk $end
$var wire 32 ) din [31:0] $end
$var reg 32 * dout [31:0] $end
$var integer 32 + i [31:0] $end
$upscope $end
$upscope $end
$enddefinitions $end
#0
$dumpvars
bx +
bx *
b0 )
b0 (
b0 '
b0 &
b0 %
0$
b0 #
b0 "
bx !
$end
#5000
b100 +
1$
#10000
b11011110101011011011111011101111 %
b11011110101011011011111011101111 )
b10 "
b10 '
b1111 #
b1111 (
0$
#15000
b100 +
1$
#20000
b1111111100000000 %
b1111111100000000 )
b10 #
b10 (
0$
#25000
b11011110101011011011111011101111 !
b11011110101011011011111011101111 *
b100 +
1$
#30000
b0 #
b0 (
0$
#35000
b11011110101011011111111111101111 !
b11011110101011011111111111101111 *
b100 +
1$
