data/ip_library/mem_sram_dp/rtl/sram_dp.v
// True dual-port synchronous SRAM — two independent read/write ports.
module sram_dp #(parameter DW = 8, parameter AW = 8) (
    input              clk,
    input              we_a, input [AW-1:0] addr_a, input [DW-1:0] din_a, output reg [DW-1:0] dout_a,
    input              we_b, input [AW-1:0] addr_b, input [DW-1:0] din_b, output reg [DW-1:0] dout_b
);
    reg [DW-1:0] mem [0:(1<<AW)-1];
    always @(posedge clk) begin
        if (we_a) mem[addr_a] <= din_a;
        dout_a <= mem[addr_a];
    end
    always @(posedge clk) begin
        if (we_b) mem[addr_b] <= din_b;
        dout_b <= mem[addr_b];
    end
endmodule

data/ip_library/mem_sram_dp/tb/sram_dp_tb.v
`timescale 1ns/1ps
module sram_dp_tb;
    localparam DW=8, AW=4;
    reg clk=0; reg we_a=0,we_b=0; reg [AW-1:0] aa=0,ab=0; reg [DW-1:0] da=0,db=0; wire [DW-1:0] qa,qb;
    integer i, errors=0;
    sram_dp #(.DW(DW),.AW(AW)) dut(.clk(clk),.we_a(we_a),.addr_a(aa),.din_a(da),.dout_a(qa),
                                   .we_b(we_b),.addr_b(ab),.din_b(db),.dout_b(qb));
    always #5 clk=~clk;
    initial begin
        $dumpfile("design.vcd"); $dumpvars(0, sram_dp_tb);
        for (i=0;i<8;i=i+1) begin @(negedge clk); we_a=1; aa=i; da=i+10; end
        @(negedge clk); we_a=0;
        for (i=0;i<8;i=i+1) begin @(negedge clk); ab=i; @(posedge clk); #1;
            if (qb !== (i+10)) begin errors=errors+1; $display("MISMATCH %0d",i); end end
        if (errors==0) $display("PASS: dual-port SRAM ok"); else $display("FAIL: %0d errors", errors);
        $finish;
    end
endmodule

data/ip_library/mem_sram_dp/tb/design.vcd
$date
	Mon Jun 22 16:02:54 2026
$end
$version
	Icarus Verilog
$end
$timescale
	1ps
$end
$scope module sram_dp_tb $end
$var wire 8 ! qb [7:0] $end
$var wire 8 " qa [7:0] $end
$var reg 4 # aa [3:0] $end
$var reg 4 $ ab [3:0] $end
$var reg 1 % clk $end
$var reg 8 & da [7:0] $end
$var reg 8 ' db [7:0] $end
$var reg 1 ( we_a $end
$var reg 1 ) we_b $end
$var integer 32 * errors [31:0] $end
$var integer 32 + i [31:0] $end
$scope module dut $end
$var wire 4 , addr_a [3:0] $end
$var wire 4 - addr_b [3:0] $end
$var wire 1 % clk $end
$var wire 8 . din_a [7:0] $end
$var wire 8 / din_b [7:0] $end
$var wire 1 ( we_a $end
$var wire 1 ) we_b $end
$var reg 8 0 dout_a [7:0] $end
$var reg 8 1 dout_b [7:0] $end
$upscope $end
$upscope $end
$enddefinitions $end
#0
$dumpvars
bx 1
bx 0
b0 /
b0 .
b0 -
b0 ,
b0 +
b0 *
0)
0(
b0 '
b0 &
0%
b0 $
b0 #
bx "
bx !
$end
#5000
1%
#10000
b1 +
b1010 &
b1010 .
1(
0%
#15000
1%
#20000
b10 +
b1011 &
b1011 .
b1 #
b1 ,
0%
#25000
b1010 !
b1010 1
1%
#30000
b11 +
b1100 &
b1100 .
b10 #
b10 ,
0%
#35000
1%
#40000
b100 +
b1101 &
b1101 .
b11 #
b11 ,
0%
#45000
1%
#50000
b101 +
b1110 &
b1110 .
b100 #
b100 ,
0%
#55000
1%
#60000
b110 +
b1111 &
b1111 .
b101 #
b101 ,
0%
#65000
1%
#70000
b111 +
b10000 &
b10000 .
b110 #
b110 ,
0%
#75000
1%
#80000
b1000 +
b10001 &
b10001 .
b111 #
b111 ,
0%
#85000
1%
#90000
b0 +
0(
0%
#95000
b10001 "
b10001 0
1%
#100000
0%
#105000
1%
#106000
b1 +
#110000
b1 $
b1 -
0%
#115000
b1011 !
b1011 1
1%
#116000
b10 +
#120000
b10 $
b10 -
0%
#125000
b1100 !
b1100 1
1%
#126000
b11 +
#130000
b11 $
b11 -
0%
#135000
b1101 !
b1101 1
1%
#136000
b100 +
#140000
b100 $
b100 -
0%
#145000
b1110 !
b1110 1
1%
#146000
b101 +
#150000
b101 $
b101 -
0%
#155000
b1111 !
b1111 1
1%
#156000
b110 +
#160000
b110 $
b110 -
0%
#165000
b10000 !
b10000 1
1%
#166000
b111 +
#170000
b111 $
b111 -
0%
#175000
b10001 !
b10001 1
1%
#176000
b1000 +
